COPYING.LGPLv3
LICENSE
MANIFEST.in
README.md
ez_setup.py
requirements.txt
setup.py
django_pageguide.egg-info/PKG-INFO
django_pageguide.egg-info/SOURCES.txt
django_pageguide.egg-info/dependency_links.txt
django_pageguide.egg-info/requires.txt
django_pageguide.egg-info/top_level.txt
pageguide/__init__.py
pageguide/admin.py
pageguide/models.py
pageguide/views.py
pageguide/locale/es/LC_MESSAGES/django.mo
pageguide/locale/es/LC_MESSAGES/django.po
pageguide/migrations/0001_initial.py
pageguide/migrations/__init__.py
pageguide/static/pageguide/pageguide.min.css
pageguide/static/pageguide/pageguide.min.js
pageguide/templates/pageguide/pageguide.html
pageguide/templates/pageguide/pageguide_css.html
pageguide/templates/pageguide/pageguide_js.html
pageguide/templatetags/__init__.py
pageguide/templatetags/pageguide_tags.py